dataeval/__init__.py
dataeval/_log.py
dataeval/config.py
dataeval/data/__init__.py
dataeval/data/_embeddings.py
dataeval/data/_images.py
dataeval/data/_metadata.py
dataeval/data/_selection.py
dataeval/data/_split.py
dataeval/data/_targets.py
dataeval/data/selections/__init__.py
dataeval/data/selections/_classbalance.py
dataeval/data/selections/_classfilter.py
dataeval/data/selections/_indices.py
dataeval/data/selections/_limit.py
dataeval/data/selections/_prioritize.py
dataeval/data/selections/_reverse.py
dataeval/data/selections/_shuffle.py
dataeval/detectors/__init__.py
dataeval/detectors/drift/__init__.py
dataeval/detectors/drift/_base.py
dataeval/detectors/drift/_cvm.py
dataeval/detectors/drift/_ks.py
dataeval/detectors/drift/_mmd.py
dataeval/detectors/drift/_uncertainty.py
dataeval/detectors/drift/updates.py
dataeval/detectors/linters/__init__.py
dataeval/detectors/linters/duplicates.py
dataeval/detectors/linters/outliers.py
dataeval/detectors/ood/__init__.py
dataeval/detectors/ood/ae.py
dataeval/detectors/ood/base.py
dataeval/detectors/ood/mixin.py
dataeval/detectors/ood/vae.py
dataeval/metadata/__init__.py
dataeval/metadata/_distance.py
dataeval/metadata/_ood.py
dataeval/metadata/_utils.py
dataeval/metrics/__init__.py
dataeval/metrics/bias/__init__.py
dataeval/metrics/bias/_balance.py
dataeval/metrics/bias/_completeness.py
dataeval/metrics/bias/_coverage.py
dataeval/metrics/bias/_diversity.py
dataeval/metrics/bias/_parity.py
dataeval/metrics/estimators/__init__.py
dataeval/metrics/estimators/_ber.py
dataeval/metrics/estimators/_clusterer.py
dataeval/metrics/estimators/_divergence.py
dataeval/metrics/estimators/_uap.py
dataeval/metrics/stats/__init__.py
dataeval/metrics/stats/_base.py
dataeval/metrics/stats/_boxratiostats.py
dataeval/metrics/stats/_dimensionstats.py
dataeval/metrics/stats/_hashstats.py
dataeval/metrics/stats/_imagestats.py
dataeval/metrics/stats/_labelstats.py
dataeval/metrics/stats/_pixelstats.py
dataeval/metrics/stats/_visualstats.py
dataeval-1.0.0.dist-info/LICENSE.txt
dataeval-1.0.0.dist-info/METADATA
dataeval-1.0.0.dist-info/WHEEL
dataeval-1.0.0.dist-info/RECORD
