Metadata-Version: 2.1
Name: dataeval
Version: 1.0.0
Summary: DataEval provides a simple interface to characterize image data and its impact on model performance across classification and object-detection tasks
Home-page: https://dataeval.ai/
License: MIT
Author: Andrew Weng
Author-email: andrew.weng@ariacoustics.com
Maintainer: ARiA
Maintainer-email: dataeval@ariacoustics.com
Requires-Python: >=3.9,<3.13
Classifier: Development Status :: 4 - Beta
Classifier: Intended Audience :: Science/Research
Classifier: License :: OSI Approved :: MIT License
Classifier: Operating System :: OS Independent
Classifier: Programming Language :: Python :: 3
Classifier: Programming Language :: Python :: 3.9
Classifier: Programming Language :: Python :: 3.10
Classifier: Programming Language :: Python :: 3.11
Classifier: Programming Language :: Python :: 3.12
Classifier: Programming Language :: Python :: 3 :: Only
Classifier: Topic :: Scientific/Engineering
Provides-Extra: all
Requires-Dist: defusedxml (>=0.7.1)
Requires-Dist: fast_hdbscan (==0.2.0)
Requires-Dist: matplotlib (>=3.7.1) ; extra == "all"
Requires-Dist: numba (>=0.59.1)
Requires-Dist: numpy (>=1.24.2)
Requires-Dist: pandas (>=2.0) ; extra == "all"
Requires-Dist: pillow (>=10.3.0)
Requires-Dist: requests
Requires-Dist: scikit-learn (>=1.5.0)
Requires-Dist: scipy (>=1.10)
Requires-Dist: torch (>=2.2.0)
Requires-Dist: torchvision (>=0.17.0)
Requires-Dist: tqdm
Requires-Dist: typing-extensions (>=4.12) ; python_version >= "3.9" and python_version < "4.0"
Requires-Dist: xxhash (>=3.3)
Project-URL: Documentation, https://dataeval.readthedocs.io/
Project-URL: Repository, https://github.com/aria-ml/dataeval/
